yaerrrr/AbstarctYaerrrrScript.py
yaerrrr/__init__.py
yaerrrr/models.py
yaerrrr/version.py
yaerrrr-1.14.4.dist-info/METADATA
yaerrrr-1.14.4.dist-info/WHEEL
yaerrrr-1.14.4.dist-info/top_level.txt
yaerrrr-1.14.4.dist-info/RECORD
