Metadata-Version: 2.1
Name: yaerrrr
Version: 1.14.4
Summary: Generate ER diagrams with python and graphviz
Home-page: https://github.com/Koldar/yaerrrr
Author: Massimo Bono
Author-email: massimobono1@gmail.com
License: UNKNOWN
Platform: UNKNOWN
Classifier: Programming Language :: Python :: 3
Classifier: License :: OSI Approved :: MIT License
Classifier: Operating System :: OS Independent
Requires-Python: >=3.6
Requires-Dist: decorator
Requires-Dist: networkx
